starlette_templates/__init__.py
starlette_templates/context.py
starlette_templates/errors.py
starlette_templates/forms.py
starlette_templates/hypertext.py
starlette_templates/middleware.py
starlette_templates/responses.py
starlette_templates/routing.py
starlette_templates/staticfiles.py
starlette_templates/components/__init__.py
starlette_templates/components/base.py
starlette_templates/components/bootstrap.py
starlette_templates/components/forms.py
starlette_templates/templates/error.html
starlette_templates/templates/components/bootstrap/accordion.html
starlette_templates/templates/components/bootstrap/activity_item.html
starlette_templates/templates/components/bootstrap/alert.html
starlette_templates/templates/components/bootstrap/avatar.html
starlette_templates/templates/components/bootstrap/badge.html
starlette_templates/templates/components/bootstrap/breadcrumb.html
starlette_templates/templates/components/bootstrap/button.html
starlette_templates/templates/components/bootstrap/button_group.html
starlette_templates/templates/components/bootstrap/card.html
starlette_templates/templates/components/bootstrap/carousel.html
starlette_templates/templates/components/bootstrap/col.html
starlette_templates/templates/components/bootstrap/collapse.html
starlette_templates/templates/components/bootstrap/container.html
starlette_templates/templates/components/bootstrap/copy_button.html
starlette_templates/templates/components/bootstrap/divider.html
starlette_templates/templates/components/bootstrap/dropdown.html
starlette_templates/templates/components/bootstrap/empty_state.html
starlette_templates/templates/components/bootstrap/filter_bar.html
starlette_templates/templates/components/bootstrap/grid.html
starlette_templates/templates/components/bootstrap/icon.html
starlette_templates/templates/components/bootstrap/list_group.html
starlette_templates/templates/components/bootstrap/modal.html
starlette_templates/templates/components/bootstrap/navbar.html
starlette_templates-0.0.1a7.dist-info/licenses/LICENSE
starlette_templates-0.0.1a7.dist-info/METADATA
starlette_templates-0.0.1a7.dist-info/WHEEL
starlette_templates-0.0.1a7.dist-info/top_level.txt
starlette_templates-0.0.1a7.dist-info/RECORD
