Metadata-Version: 2.4
Name: starlette-templates
Version: 0.0.1a7
Summary: Extends Starlette with support for template-driven routing, form handling, and reusable UI components, built on Jinja2 and Pydantic.
Author-email: Tycho Engineering <tychoengr@gmail.com>
Keywords: web,starlette,jinja2
Classifier: Programming Language :: Python :: 3.12
Classifier: Programming Language :: Python :: 3.11
Classifier: Programming Language :: Python :: 3.10
Classifier: License :: OSI Approved :: MIT License
Classifier: Operating System :: OS Independent
Classifier: Environment :: Web Environment
Classifier: Topic :: Internet :: WWW/HTTP
Requires-Python: >=3.10
License-File: LICENSE
Requires-Dist: starlette>=0.48.0
Requires-Dist: jinja2>=3.1.6
Requires-Dist: pydantic>=2.11.9
Requires-Dist: xxhash>=3.5.0
Requires-Dist: python-multipart>=0.0.20
Requires-Dist: aiofiles>=25.1.0
Requires-Dist: Markdown>=3.10
Requires-Dist: pymdown-extensions>=10.19.1
Requires-Dist: Pygments>=2.19.2
Provides-Extra: dev
Requires-Dist: ruff; extra == "dev"
Requires-Dist: ipykernel; extra == "dev"
Requires-Dist: pytest; extra == "dev"
Requires-Dist: pytest-cov; extra == "dev"
Requires-Dist: nbformat; extra == "dev"
Requires-Dist: setuptools; extra == "dev"
Requires-Dist: wheel; extra == "dev"
Requires-Dist: twine; extra == "dev"
Requires-Dist: build; extra == "dev"
Requires-Dist: uvicorn>=0.37.0; extra == "dev"
Requires-Dist: httpx>=0.28.1; extra == "dev"
Requires-Dist: mypy>=1.17.1; extra == "dev"
Requires-Dist: pytest-asyncio>=1.1.0; extra == "dev"
Requires-Dist: mkdocs; extra == "dev"
Requires-Dist: mkdocs-material; extra == "dev"
Requires-Dist: mkdocstrings-python; extra == "dev"
Requires-Dist: mkdocs-redirects; extra == "dev"
Requires-Dist: mkdocs-awesome-pages-plugin; extra == "dev"
Requires-Dist: mkdocs-autorefs; extra == "dev"
Requires-Dist: mkdocs-llmstxt; extra == "dev"
Dynamic: license-file
